copier/__init__.py
mkdocs_homepage_copier-1.0.0.dist-info/LICENSE
mkdocs_homepage_copier-1.0.0.dist-info/METADATA
mkdocs_homepage_copier-1.0.0.dist-info/WHEEL
mkdocs_homepage_copier-1.0.0.dist-info/entry_points.txt
mkdocs_homepage_copier-1.0.0.dist-info/top_level.txt
mkdocs_homepage_copier-1.0.0.dist-info/RECORD
