Metadata-Version: 2.1
Name: mkdocs-homepage-copier
Version: 1.0.0
Summary: Reuse the README.md file by copying it into the docs/ directory as the docs/index.md file
Home-page: https://github.com/onyonkaclifford/MkDocs-homepage-copier
Author: Clifford Onyonka
Author-email: jsjamessakho@gmail.com
Maintainer: Clifford Onyonka
Maintainer-email: jsjamessakho@gmail.com
License: MIT
Classifier: Programming Language :: Python :: 3
Classifier: Operating System :: OS Independent
Classifier: License :: OSI Approved :: MIT License
Requires-Python: >=3.7
License-File: LICENSE
Requires-Dist: mkdocs
